lumecode/__init__.py
lumecode/__version__.py
lumecode/backend/agents/__init__.py
lumecode/backend/agents/base.py
lumecode/backend/agents/code_review.py
lumecode/backend/agents/communication.py
lumecode/backend/agents/processor.py
lumecode/backend/agents/refactoring.py
lumecode/backend/agents/runtime.py
lumecode/backend/agents/sandbox.py
lumecode/backend/config/__init__.py
lumecode/backend/config/manager.py
lumecode/backend/docs/__init__.py
lumecode/backend/docs/generator.py
lumecode/cli/__init__.py
lumecode/cli/main.py
lumecode/cli/setup.py
lumecode/cli/commands/__init__.py
lumecode/cli/commands/ask.py
lumecode/cli/commands/batch.py
lumecode/cli/commands/cache.py
lumecode/cli/commands/chat.py
lumecode/cli/commands/commit.py
lumecode/cli/commands/config.py
lumecode/cli/commands/docs.py
lumecode/cli/commands/explain.py
lumecode/cli/commands/file.py
lumecode/cli/commands/provider.py
lumecode/cli/commands/refactor.py
lumecode/cli/commands/review.py
lumecode/cli/commands/test.py
lumecode/cli/core/__init__.py
lumecode/cli/core/cache.py
lumecode/cli/core/config.py
lumecode/cli/core/session.py
lumecode/cli/core/context/__init__.py
lumecode/cli/core/context/code_parser.py
lumecode/cli/core/context/files.py
lumecode/cli/core/context/git.py
lumecode/cli/core/context/manager.py
lumecode/cli/core/context/prioritizer.py
lumecode/cli/core/context/tokenizer.py
lumecode/cli/core/llm/__init__.py
lumecode/cli/core/llm/base.py
lumecode/cli/core/llm/groq.py
lumecode/cli/core/llm/mock.py
lumecode/cli/core/llm/openrouter.py
lumecode/cli/core/prompts/__init__.py
lumecode/cli/core/prompts/context.py
lumecode/cli/core/prompts/templates.py
lumecode/cli/core/refactor/__init__.py
lumecode/cli/core/refactor/parser.py
lumecode/cli/core/review/__init__.py
lumecode/cli/core/review/parser.py
lumecode/cli/core/ui/__init__.py
lumecode/cli/core/ui/streaming.py
lumecode-1.0.1.dist-info/licenses/LICENSE
lumecode-1.0.1.dist-info/METADATA
lumecode-1.0.1.dist-info/WHEEL
lumecode-1.0.1.dist-info/entry_points.txt
lumecode-1.0.1.dist-info/top_level.txt
lumecode-1.0.1.dist-info/RECORD
