Metadata-Version: 2.4
Name: lumecode
Version: 1.0.1
Summary: AI-powered developer CLI assistant - FREE, open-source, intelligent
Author-email: Lumecode Contributors <support@lumecode.dev>
License-Expression: MIT
Project-URL: Homepage, https://github.com/anonymus-netizien/lumecode
Project-URL: Documentation, https://github.com/anonymus-netizien/lumecode#readme
Project-URL: Repository, https://github.com/anonymus-netizien/lumecode
Project-URL: Bug Tracker, https://github.com/anonymus-netizien/lumecode/issues
Keywords: ai,cli,developer-tools,code-assistant,llm,groq,openrouter,code-review,test-generation,documentation
Classifier: Development Status :: 4 - Beta
Classifier: Intended Audience :: Developers
Classifier: Topic :: Software Development :: Code Generators
Classifier: Topic :: Software Development :: Documentation
Classifier: Topic :: Software Development :: Quality Assurance
Classifier: Topic :: Software Development :: Testing
Classifier: Programming Language :: Python :: 3
Classifier: Programming Language :: Python :: 3.10
Classifier: Programming Language :: Python :: 3.11
Classifier: Programming Language :: Python :: 3.12
Classifier: Operating System :: OS Independent
Classifier: Environment :: Console
Classifier: Natural Language :: English
Requires-Python: >=3.10
License-File: LICENSE
Requires-Dist: click>=8.1.0
Requires-Dist: rich>=13.7.0
Requires-Dist: httpx>=0.27.0
Requires-Dist: python-dotenv>=1.0.0
Requires-Dist: pydantic>=2.6.0
Requires-Dist: prompt-toolkit>=3.0.0
Requires-Dist: tiktoken>=0.5.0
Provides-Extra: dev
Requires-Dist: pytest>=8.0.0; extra == "dev"
Requires-Dist: pytest-cov>=4.1.0; extra == "dev"
Requires-Dist: pytest-asyncio>=0.23.0; extra == "dev"
Requires-Dist: pytest-mock>=3.12.0; extra == "dev"
Requires-Dist: pytest-xdist>=3.5.0; extra == "dev"
Requires-Dist: pytest-timeout>=2.2.0; extra == "dev"
Requires-Dist: pytest-benchmark>=4.0.0; extra == "dev"
Requires-Dist: hypothesis>=6.92.0; extra == "dev"
Requires-Dist: black>=24.0.0; extra == "dev"
Requires-Dist: isort>=5.13.0; extra == "dev"
Requires-Dist: flake8>=7.0.0; extra == "dev"
Dynamic: license-file
